README.md
setup.cfg
setup.py
qtfn/__init__.py
qtfn.egg-info/PKG-INFO
qtfn.egg-info/SOURCES.txt
qtfn.egg-info/dependency_links.txt
qtfn.egg-info/requires.txt
qtfn.egg-info/top_level.txt