Metadata-Version: 2.1
Name: qtfn
Version: 0.1
Summary: fortnite lobbybot
Home-page: UNKNOWN
Author: mellofn
License: UNKNOWN
Platform: UNKNOWN
Classifier: Programming Language :: Python :: 3
Classifier: License :: OSI Approved :: MIT License
Classifier: Operating System :: OS Independent
